README.md
setup.py
mindey/__init__.py
mindey.egg-info/PKG-INFO
mindey.egg-info/SOURCES.txt
mindey.egg-info/dependency_links.txt
mindey.egg-info/not-zip-safe
mindey.egg-info/requires.txt
mindey.egg-info/top_level.txt