Metadata-Version: 2.1
Name: mindey
Version: 0.0.0
Summary: Shares my contact info.
Home-page: https://gitlab.com/mindey
Author: Mindey
Author-email: mindey@qq.com
License: UNDEFINED
Platform: UNKNOWN
Provides-Extra: test
